tconf/__init__.py
tconf/adapters.py
tconf/meta.py
tconf-0.58.dist-info/LICENSE
tconf-0.58.dist-info/METADATA
tconf-0.58.dist-info/WHEEL
tconf-0.58.dist-info/top_level.txt
tconf-0.58.dist-info/RECORD
