Metadata-Version: 2.1
Name: tconf
Version: 0.58
Summary: It's turtles all the way down…
Home-page: https://github.com/mixmastamyk/tconf
Author: Mike Miller
Author-email: mixmastamyk@github.com
License: LGPLv3
Project-URL: Repository, https://github.com/mixmastamyk/tconf
Project-URL: Issues, https://github.com/mixmastamyk/tconf/issues
Keywords: configuration cascade cascading ini conf yaml xml environment
Platform: UNKNOWN
Classifier: Development Status :: 3 - Alpha
Classifier: Intended Audience :: Developers
Classifier: Intended Audience :: System Administrators
Classifier: License :: OSI Approved :: GNU Lesser General Public License v3 (LGPLv3)
Classifier: Operating System :: MacOS :: MacOS X
Classifier: Operating System :: Microsoft :: Windows
Classifier: Operating System :: POSIX :: Linux
Classifier: Programming Language :: Python
Classifier: Programming Language :: Python :: 3.6
Classifier: Topic :: System :: Systems Administration
Classifier: Topic :: Utilities
Requires-Python: >=3.6
Requires-Dist: appdirs
Requires-Dist: typeguard
Provides-Extra: xml
Requires-Dist: xmltodict ; extra == 'xml'
Provides-Extra: yaml
Requires-Dist: strictyaml ; extra == 'yaml'
